ConSequences/ConSequences.py
ConSequences/__init__.py
ConSequences-0.1.data/scripts/delineateSegmentsOnReference.py
ConSequences-0.1.data/scripts/findCircularScaffolds.py
ConSequences-0.1.data/scripts/generateReferenceMSA.py
ConSequences-0.1.data/scripts/querySegmentInRawReads.py
ConSequences-0.1.dist-info/LICENSE
ConSequences-0.1.dist-info/METADATA
ConSequences-0.1.dist-info/WHEEL
ConSequences-0.1.dist-info/top_level.txt
ConSequences-0.1.dist-info/RECORD
