Metadata-Version: 2.1
Name: ConSequences
Version: 0.1
Summary: Suite to delineate contiguous and conserved sequences from assemblies and search for their presence in raw sequencing data.
Home-page: http://github.com/broadinstitute/ConSequences/
Author: Rauf Salamzade
Author-email: salamzader@gmail.com
License: BSD-3
Platform: UNKNOWN
